catframes/__init__.py
catframes/catframes.py
catframes/catmanager.py
catframes-2024.8.3.dist-info/LICENSE.txt
catframes-2024.8.3.dist-info/METADATA
catframes-2024.8.3.dist-info/WHEEL
catframes-2024.8.3.dist-info/entry_points.txt
catframes-2024.8.3.dist-info/top_level.txt
catframes-2024.8.3.dist-info/RECORD
