Metadata-Version: 2.1
Name: catframes
Version: 2024.8.3
Summary: Concatenate frames.
Author-email: Georgy Ustinov <inbox@itustinov.ru>, Bogdan Syrovatsky <bogdansir1807@gmail.com>, Evgeny Ockatiev <evgeny.ockatiev@gmail.com>
License: © Георгий Устинов, 2022–2024
Project-URL: Homepage, https://itustinov.ru/
Project-URL: Source code, https://github.com/georgy7/catframes
Project-URL: Changelog, https://github.com/georgy7/catframes/blob/main/CHANGELOG.md
Keywords: concat,images,video,webm,mp4,slideshow,timelapse,stop motion
Classifier: Intended Audience :: Developers
Classifier: Intended Audience :: System Administrators
Classifier: Topic :: Multimedia :: Video
Classifier: Topic :: Multimedia :: Graphics :: Graphics Conversion
Classifier: License :: OSI Approved :: zlib/libpng License
Requires-Python: >=3.7
License-File: LICENSE.txt
Requires-Dist: Pillow>=9.2.0
